[{"name":"sql.active_record","payload":{"sql":"SELECT  `facilities`.* FROM `facilities` WHERE `facilities`.`id` = 3 LIMIT 1","name":"Facility Load","binds":[],"type_casted_binds":[],"statement_name":null,"connection_id":70309391520140,"line":28,"filename":"/Users/ikedaryo/projects/sourcetree/saunaapp4/app/controllers/comments_controller.rb","method":"set_facility"},"time":"2019-03-29T20:48:43.607+09:00","transaction_id":"750be07f24cc7bb1d46d","end":"2019-03-29T20:48:43.609+09:00","children":[],"duration":2.276},{"name":"sql.active_record","payload":{"sql":"SELECT  `users`.* FROM `users` WHERE `users`.`id` = 104 ORDER BY `users`.`id` ASC LIMIT 1","name":"User Load","binds":[],"type_casted_binds":[],"statement_name":null,"connection_id":70309391520140,"line":24,"filename":"/Users/ikedaryo/projects/sourcetree/saunaapp4/app/controllers/comments_controller.rb","method":"comment_params"},"time":"2019-03-29T20:48:43.612+09:00","transaction_id":"750be07f24cc7bb1d46d","end":"2019-03-29T20:48:43.618+09:00","children":[],"duration":6.018},{"name":"sql.active_record","payload":{"sql":"BEGIN","name":null,"binds":[],"type_casted_binds":[],"statement_name":null,"connection_id":70309391520140,"line":5,"filename":"/Users/ikedaryo/projects/sourcetree/saunaapp4/app/controllers/comments_controller.rb","method":"create"},"time":"2019-03-29T20:48:43.620+09:00","transaction_id":"750be07f24cc7bb1d46d","end":"2019-03-29T20:48:43.624+09:00","children":[],"duration":3.7889999999999997},{"name":"sql.active_record","payload":{"sql":"SELECT  `users`.* FROM `users` WHERE `users`.`id` = 104 LIMIT 1","name":"User Load","binds":[],"type_casted_binds":[],"statement_name":null,"connection_id":70309391520140,"line":5,"filename":"/Users/ikedaryo/projects/sourcetree/saunaapp4/app/controllers/comments_controller.rb","method":"create"},"time":"2019-03-29T20:48:43.626+09:00","transaction_id":"750be07f24cc7bb1d46d","end":"2019-03-29T20:48:43.627+09:00","children":[],"duration":1.269},{"name":"sql.active_record","payload":{"sql":"SELECT  `facilities`.* FROM `facilities` WHERE `facilities`.`id` = 3 LIMIT 1","name":"Facility Load","binds":[],"type_casted_binds":[],"statement_name":null,"connection_id":70309391520140,"line":5,"filename":"/Users/ikedaryo/projects/sourcetree/saunaapp4/app/controllers/comments_controller.rb","method":"create"},"time":"2019-03-29T20:48:43.629+09:00","transaction_id":"750be07f24cc7bb1d46d","end":"2019-03-29T20:48:43.631+09:00","children":[],"duration":1.991},{"name":"sql.active_record","payload":{"sql":"INSERT INTO `comments` (`user_id`, `facility_id`, `text`, `created_at`, `updated_at`) VALUES (104, 3, 'コメント３', '2019-03-29 11:48:43', '2019-03-29 11:48:43')","name":"Comment Create","binds":[],"type_casted_binds":[],"statement_name":null,"connection_id":70309391520140,"line":5,"filename":"/Users/ikedaryo/projects/sourcetree/saunaapp4/app/controllers/comments_controller.rb","method":"create"},"time":"2019-03-29T20:48:43.632+09:00","transaction_id":"750be07f24cc7bb1d46d","end":"2019-03-29T20:48:43.635+09:00","children":[],"duration":2.6350000000000002},{"name":"sql.active_record","payload":{"sql":"COMMIT","name":null,"binds":[],"type_casted_binds":[],"statement_name":null,"connection_id":70309391520140,"line":5,"filename":"/Users/ikedaryo/projects/sourcetree/saunaapp4/app/controllers/comments_controller.rb","method":"create"},"time":"2019-03-29T20:48:43.638+09:00","transaction_id":"750be07f24cc7bb1d46d","end":"2019-03-29T20:48:43.642+09:00","children":[],"duration":3.1020000000000003},{"name":"sql.active_record","payload":{"sql":"BEGIN","name":null,"binds":[],"type_casted_binds":[],"statement_name":null,"connection_id":70309391520140,"line":6,"filename":"/Users/ikedaryo/projects/sourcetree/saunaapp4/app/controllers/comments_controller.rb","method":"create"},"time":"2019-03-29T20:48:43.642+09:00","transaction_id":"750be07f24cc7bb1d46d","end":"2019-03-29T20:48:43.643+09:00","children":[],"duration":0.858},{"name":"sql.active_record","payload":{"sql":"COMMIT","name":null,"binds":[],"type_casted_binds":[],"statement_name":null,"connection_id":70309391520140,"line":6,"filename":"/Users/ikedaryo/projects/sourcetree/saunaapp4/app/controllers/comments_controller.rb","method":"create"},"time":"2019-03-29T20:48:43.644+09:00","transaction_id":"750be07f24cc7bb1d46d","end":"2019-03-29T20:48:43.646+09:00","children":[],"duration":1.509},{"name":"process_action.action_controller","payload":{"controller":"CommentsController","action":"create","params":{"utf8":"✓","authenticity_token":"sboWxGvHEDsu30E3gmcp0y2246/oMRtG2ivkt5evdDe8nSyzfVxaQfzt2UPm6/GjodCuJixQmxOwAdVpMsx+EA==","comment":{"text":"コメント３"},"commit":"コメント送信","controller":"comments","action":"create","facility_id":"3"},"headers":{"SCRIPT_NAME":"","QUERY_STRING":"","SERVER_PROTOCOL":"HTTP/1.1","SERVER_SOFTWARE":"puma 3.12.0 Llamas in Pajamas","GATEWAY_INTERFACE":"CGI/1.2","REQUEST_METHOD":"POST","REQUEST_PATH":"/facilities/3/comments","REQUEST_URI":"/facilities/3/comments","HTTP_VERSION":"HTTP/1.1","HTTP_HOST":"localhost:3000","HTTP_CONNECTION":"keep-alive","CONTENT_LENGTH":"258","HTTP_CACHE_CONTROL":"max-age=0","HTTP_ORIGIN":"http://localhost:3000","HTTP_UPGRADE_INSECURE_REQUESTS":"1","CONTENT_TYPE":"application/x-www-form-urlencoded","HTTP_USER_AGENT":"Mozilla/5.0 (Macintosh; Intel Mac OS X 10_14_3) AppleWebKit/537.36 (KHTML, like Gecko) Chrome/71.0.3578.98 Safari/537.36","HTTP_ACCEPT":"text/html,application/xhtml+xml,application/xml;q=0.9,image/webp,image/apng,*/*;q=0.8","HTTP_REFERER":"http://localhost:3000/facilities/3","HTTP_ACCEPT_ENCODING":"gzip, deflate, br","HTTP_ACCEPT_LANGUAGE":"ja,en-US;q=0.9,en;q=0.8","HTTP_COOKIE":"_ga=GA1.1.1051144753.1546925867; _saunaapp2_session=nOzwZZsCOqjWJOLtgSeqYxsQwcvDgKN97l%2BaVW5Nk7Ctbsk%2Bn3UMG%2B%2F0c6OFOxF4coAaQ6Uq%2Fa87tR%2B3bAj0OfPPNgA2EDtPrMk6ZaPn3Aqd9dBOY%2Fju05%2FV7tjA%2Bemjv7Qa%2BCz%2FtcNPD7UdmqLbRvKNa43M2jovkPZ2jzN6KLRd9u6z2VHVpw729VzgaZYF%2BSsoXzQnmKvCw2l6lGfrW7npvDHf43IJGPmzzF8%3D--IHxwfpqUv4niPAql--Pg5tKyCCd47d0zvhCO9e0A%3D%3D","SERVER_NAME":"localhost","SERVER_PORT":"3000","PATH_INFO":"/facilities/3/comments","REMOTE_ADDR":"127.0.0.1","ROUTES_70309344543160_SCRIPT_NAME":"","ORIGINAL_FULLPATH":"/facilities/3/comments","ORIGINAL_SCRIPT_NAME":""},"format":"html","method":"POST","path":"/facilities/3/comments","status":302,"view_runtime":null,"db_runtime":14.088000636547804},"time":"2019-03-29T20:48:43.605+09:00","transaction_id":"c1e4fa92ee311272acb9","end":"2019-03-29T20:48:43.647+09:00","children":[],"duration":41.755}]