[{"name":"sql.active_record","payload":{"sql":"SELECT  `facilities`.* FROM `facilities` WHERE `facilities`.`id` = 3 LIMIT 1","name":"Facility Load","binds":[],"type_casted_binds":[],"statement_name":null,"connection_id":70309391520140,"line":28,"filename":"/Users/ikedaryo/projects/sourcetree/saunaapp4/app/controllers/comments_controller.rb","method":"set_facility"},"time":"2019-03-29T20:48:58.591+09:00","transaction_id":"750be07f24cc7bb1d46d","end":"2019-03-29T20:48:58.595+09:00","children":[],"duration":3.332},{"name":"sql.active_record","payload":{"sql":"SELECT  `users`.* FROM `users` WHERE `users`.`id` = 104 ORDER BY `users`.`id` ASC LIMIT 1","name":"User Load","binds":[],"type_casted_binds":[],"statement_name":null,"connection_id":70309391520140,"line":24,"filename":"/Users/ikedaryo/projects/sourcetree/saunaapp4/app/controllers/comments_controller.rb","method":"comment_params"},"time":"2019-03-29T20:48:58.596+09:00","transaction_id":"750be07f24cc7bb1d46d","end":"2019-03-29T20:48:58.598+09:00","children":[],"duration":1.568},{"name":"sql.active_record","payload":{"sql":"BEGIN","name":null,"binds":[],"type_casted_binds":[],"statement_name":null,"connection_id":70309391520140,"line":5,"filename":"/Users/ikedaryo/projects/sourcetree/saunaapp4/app/controllers/comments_controller.rb","method":"create"},"time":"2019-03-29T20:48:58.599+09:00","transaction_id":"750be07f24cc7bb1d46d","end":"2019-03-29T20:48:58.600+09:00","children":[],"duration":0.829},{"name":"sql.active_record","payload":{"sql":"SELECT  `users`.* FROM `users` WHERE `users`.`id` = 104 LIMIT 1","name":"User Load","binds":[],"type_casted_binds":[],"statement_name":null,"connection_id":70309391520140,"line":5,"filename":"/Users/ikedaryo/projects/sourcetree/saunaapp4/app/controllers/comments_controller.rb","method":"create"},"time":"2019-03-29T20:48:58.601+09:00","transaction_id":"750be07f24cc7bb1d46d","end":"2019-03-29T20:48:58.604+09:00","children":[],"duration":3.0469999999999997},{"name":"sql.active_record","payload":{"sql":"SELECT  `facilities`.* FROM `facilities` WHERE `facilities`.`id` = 3 LIMIT 1","name":"Facility Load","binds":[],"type_casted_binds":[],"statement_name":null,"connection_id":70309391520140,"line":5,"filename":"/Users/ikedaryo/projects/sourcetree/saunaapp4/app/controllers/comments_controller.rb","method":"create"},"time":"2019-03-29T20:48:58.608+09:00","transaction_id":"750be07f24cc7bb1d46d","end":"2019-03-29T20:48:58.609+09:00","children":[],"duration":1.537},{"name":"sql.active_record","payload":{"sql":"INSERT INTO `comments` (`user_id`, `facility_id`, `text`, `created_at`, `updated_at`) VALUES (104, 3, 'komeny2', '2019-03-29 11:48:58', '2019-03-29 11:48:58')","name":"Comment Create","binds":[],"type_casted_binds":[],"statement_name":null,"connection_id":70309391520140,"line":5,"filename":"/Users/ikedaryo/projects/sourcetree/saunaapp4/app/controllers/comments_controller.rb","method":"create"},"time":"2019-03-29T20:48:58.611+09:00","transaction_id":"750be07f24cc7bb1d46d","end":"2019-03-29T20:48:58.612+09:00","children":[],"duration":1.5410000000000001},{"name":"sql.active_record","payload":{"sql":"COMMIT","name":null,"binds":[],"type_casted_binds":[],"statement_name":null,"connection_id":70309391520140,"line":5,"filename":"/Users/ikedaryo/projects/sourcetree/saunaapp4/app/controllers/comments_controller.rb","method":"create"},"time":"2019-03-29T20:48:58.613+09:00","transaction_id":"750be07f24cc7bb1d46d","end":"2019-03-29T20:48:58.692+09:00","children":[],"duration":79.06299999999999},{"name":"sql.active_record","payload":{"sql":"BEGIN","name":null,"binds":[],"type_casted_binds":[],"statement_name":null,"connection_id":70309391520140,"line":6,"filename":"/Users/ikedaryo/projects/sourcetree/saunaapp4/app/controllers/comments_controller.rb","method":"create"},"time":"2019-03-29T20:48:58.693+09:00","transaction_id":"750be07f24cc7bb1d46d","end":"2019-03-29T20:48:58.694+09:00","children":[],"duration":0.973},{"name":"sql.active_record","payload":{"sql":"COMMIT","name":null,"binds":[],"type_casted_binds":[],"statement_name":null,"connection_id":70309391520140,"line":6,"filename":"/Users/ikedaryo/projects/sourcetree/saunaapp4/app/controllers/comments_controller.rb","method":"create"},"time":"2019-03-29T20:48:58.695+09:00","transaction_id":"750be07f24cc7bb1d46d","end":"2019-03-29T20:48:58.696+09:00","children":[],"duration":0.7919999999999999},{"name":"process_action.action_controller","payload":{"controller":"CommentsController","action":"create","params":{"utf8":"✓","authenticity_token":"Yxq3uCx9qkEa7GcZFIii9XeW3/n2jpmPhcP46eGB5ghuPY3POubgO8je/21wBHqF+/CScDLvGdrv6ck3ROLsLw==","comment":{"text":"komeny2"},"commit":"コメント送信","controller":"comments","action":"create","facility_id":"3"},"headers":{"SCRIPT_NAME":"","QUERY_STRING":"","SERVER_PROTOCOL":"HTTP/1.1","SERVER_SOFTWARE":"puma 3.12.0 Llamas in Pajamas","GATEWAY_INTERFACE":"CGI/1.2","REQUEST_METHOD":"POST","REQUEST_PATH":"/facilities/3/comments","REQUEST_URI":"/facilities/3/comments","HTTP_VERSION":"HTTP/1.1","HTTP_HOST":"localhost:3000","HTTP_CONNECTION":"keep-alive","CONTENT_LENGTH":"222","HTTP_CACHE_CONTROL":"max-age=0","HTTP_ORIGIN":"http://localhost:3000","HTTP_UPGRADE_INSECURE_REQUESTS":"1","CONTENT_TYPE":"application/x-www-form-urlencoded","HTTP_USER_AGENT":"Mozilla/5.0 (Macintosh; Intel Mac OS X 10_14_3) AppleWebKit/537.36 (KHTML, like Gecko) Chrome/71.0.3578.98 Safari/537.36","HTTP_ACCEPT":"text/html,application/xhtml+xml,application/xml;q=0.9,image/webp,image/apng,*/*;q=0.8","HTTP_REFERER":"http://localhost:3000/facilities/3","HTTP_ACCEPT_ENCODING":"gzip, deflate, br","HTTP_ACCEPT_LANGUAGE":"ja,en-US;q=0.9,en;q=0.8","HTTP_COOKIE":"_ga=GA1.1.1051144753.1546925867; _saunaapp2_session=DrEq7pTWxFzofqoX%2FHmRY63rv89Nf1dBYH8e51KuoO99XOfLKqeOK7XV55F4HIjkTYCXOTPj6%2BKNQ84o%2BUUuYtBNXS%2Bx%2BqvauzPkR%2BC4sbJz0%2BChMEwxXYUzFaOIFoU%2FGFY%2FVuAmSwyGP5j3TjABAV3jJWf7K56u7rSWSY9M2fVQ6UpGkl52UQvJybIRHGXPdC0BdO4dPFMq8jkLk6AfSd%2BjJCUzYmL1tlYN3uY%3D--6JlIIQVvLy4%2B2ylL--zyWj4wjWfftOyWJaulJRqA%3D%3D","SERVER_NAME":"localhost","SERVER_PORT":"3000","PATH_INFO":"/facilities/3/comments","REMOTE_ADDR":"127.0.0.1","ROUTES_70309344543160_SCRIPT_NAME":"","ORIGINAL_FULLPATH":"/facilities/3/comments","ORIGINAL_SCRIPT_NAME":""},"format":"html","method":"POST","path":"/facilities/3/comments","status":302,"view_runtime":null,"db_runtime":84.34500126168132},"time":"2019-03-29T20:48:58.588+09:00","transaction_id":"750be07f24cc7bb1d46d","end":"2019-03-29T20:48:58.697+09:00","children":[],"duration":108.35300000000001}]